MANIFEST.in
README.rst
requirements.txt
setup.py
examples/config.cfg
examples/test_scripts/example_httplib.py
examples/test_scripts/example_mechanize_simple.py
examples/test_scripts/example_mechanize_wikipedia.py
examples/test_scripts/example_mock.py
examples/test_scripts/example_urllib2.py
multi_mechanize.egg-info/PKG-INFO
multi_mechanize.egg-info/SOURCES.txt
multi_mechanize.egg-info/dependency_links.txt
multi_mechanize.egg-info/entry_points.txt
multi_mechanize.egg-info/requires.txt
multi_mechanize.egg-info/top_level.txt
multimechanize/__init__.py
multimechanize/core.py
multimechanize/dependency_checker.py
multimechanize/graph.py
multimechanize/progressbar.py
multimechanize/reportwriter.py
multimechanize/reportwriterxml.py
multimechanize/results.py
multimechanize/resultsloader.py
multimechanize/resultswriter.py
multimechanize/rpcserver.py
multimechanize/utilities/__init__.py
multimechanize/utilities/gridgui.py
multimechanize/utilities/newproject.py
multimechanize/utilities/run.py