Metadata-Version: 1.0
Name: multi-mechanize
Version: 1.2.0
Summary: Multi-Mechanize - Performance Test Framework
Home-page: http://multimechanize.com
Author: Corey Goldberg
Author-email: corey@goldb.org
License: UNKNOWN
Keywords: performance,scalability,load,test,testing,benchmark
Platform: UNKNOWN
Classifier: Development Status :: 4 - Beta
Classifier: License :: OSI Approved :: GNU Library or Lesser General Public License (LGPL)
Classifier: Operating System :: OS Independent
Classifier: Programming Language :: Python
Classifier: Programming Language :: Python :: 2.6
Classifier: Programming Language :: Python :: 2.7
Classifier: Topic :: Software Development :: Testing
Classifier: Topic :: Software Development :: Testing :: Traffic Generation
Classifier: Topic :: System :: Benchmark
